README.rst
setup.cfg
setup.py
pyResMan/DESFireEx.py
pyResMan/DebuggerScriptFile.py
pyResMan/DebuggerUtils.py
pyResMan/GPInterface.py
pyResMan/Main.py
pyResMan/MifareTLV.py
pyResMan/R502Device.py
pyResMan/R502SpyLibrary.py
pyResMan/SCInterface.py
pyResMan/Util.py
pyResMan/__init__.py
pyResMan/__main__.py
pyResMan/pyLibSC.py
pyResMan/pyResManController.py
pyResMan/pyResManReader.py
pyResMan/testR502SpyLibrary.py
pyResMan.egg-info/PKG-INFO
pyResMan.egg-info/SOURCES.txt
pyResMan.egg-info/dependency_links.txt
pyResMan.egg-info/requires.txt
pyResMan.egg-info/top_level.txt
pyResMan/BaseDialogs/__init__.py
pyResMan/BaseDialogs/pyResManCommandDialogBase_ATTRIB.py
pyResMan/BaseDialogs/pyResManCommandDialogBase_AnticollisionSelect.py
pyResMan/BaseDialogs/pyResManCommandDialogBase_Basic.py
pyResMan/BaseDialogs/pyResManCommandDialogBase_HLTB.py
pyResMan/BaseDialogs/pyResManCommandDialogBase_IBlock.py
pyResMan/BaseDialogs/pyResManCommandDialogBase_MifareAuthentication.py
pyResMan/BaseDialogs/pyResManCommandDialogBase_MifareBlockRead.py
pyResMan/BaseDialogs/pyResManCommandDialogBase_MifareBlockWrite.py
pyResMan/BaseDialogs/pyResManCommandDialogBase_MifareDecrement.py
pyResMan/BaseDialogs/pyResManCommandDialogBase_MifareDecrementTransfer.py
pyResMan/BaseDialogs/pyResManCommandDialogBase_MifareIncrement.py
pyResMan/BaseDialogs/pyResManCommandDialogBase_MifareLoadKey.py
pyResMan/BaseDialogs/pyResManCommandDialogBase_MifareRestore.py
pyResMan/BaseDialogs/pyResManCommandDialogBase_MifareTransfer.py
pyResMan/BaseDialogs/pyResManCommandDialogBase_PPS.py
pyResMan/BaseDialogs/pyResManCommandDialogBase_RATS.py
pyResMan/BaseDialogs/pyResManCommandDialogBase_RBlock.py
pyResMan/BaseDialogs/pyResManCommandDialogBase_REQBWUPB.py
pyResMan/BaseDialogs/pyResManCommandDialogBase_SBlock.py
pyResMan/BaseDialogs/pyResManCommandDialogBase_SlotMarker.py
pyResMan/BaseDialogs/pyResManDESFireDialogBase_CreateApplication.py
pyResMan/BaseDialogs/pyResManDESFireDialogBase_CreateFile.py
pyResMan/BaseDialogs/pyResManDESFireDialogBase_FileOperation.py
pyResMan/BaseDialogs/pyResManDialogBase.py
pyResMan/BaseDialogs/pyResManInstallDialogBase.py
